{"cameraMode":{"drawMode":0,"name":"Shaded","section":"Shading Mode"},"sceneLighting":true,"audioPlay":false,"sceneViewState":{"m_AlwaysRefresh":true,"showFog":true,"showSkybox":true,"showFlares":true,"showImageEffects":true,"showParticleSystems":true,"showVisualEffectGraphs":true,"m_FxEnabled":true},"in2DMode":false,"pivot":{"x":5.871484279632568,"y":9.580089569091797,"z":27.95013427734375},"rotation":{"x":0.0036715699825435879,"y":0.08248702436685562,"z":-0.0014157950645312667,"w":0.9976128935813904},"size":10.0,"orthographic":false}